{
  "version": 1,
  "active": true,
  "skill": "ralph",
  "keyword": "$ralph",
  "phase": "planning",
  "activated_at": "2026-04-07T08:56:10.010Z",
  "updated_at": "2026-04-07T08:56:10.010Z",
  "source": "keyword-detector",
  "session_id": "",
  "thread_id": "019d65be-9de3-7530-b2d0-b99a1757b3ba",
  "turn_id": "019d671a-0c8d-7401-b569-2eb9bbcd2a63",
  "input_lock": {
    "active": false,
    "scope": "deep-interview-auto-approval",
    "acquired_at": "2026-04-07T05:20:26.569Z",
    "blocked_inputs": [
      "yes",
      "y",
      "proceed",
      "continue",
      "ok",
      "sure",
      "go ahead",
      "next i should"
    ],
    "message": "Deep interview is active; auto-approval shortcuts are blocked until the interview finishes.",
    "released_at": "2026-04-07T08:56:10.010Z",
    "exit_reason": "handoff"
  },
  "iteration": 1,
  "last_turn_at": "2026-04-07T08:58:06.981Z"
}